dataengineeringfunctions/__init__.py
dataengineeringfunctions/convolution2d.py
dataengineeringfunctions/transpose2d.py
dataengineeringfunctions/window1d.py
dataengineeringfunctions-0.1.0.dist-info/METADATA
dataengineeringfunctions-0.1.0.dist-info/WHEEL
dataengineeringfunctions-0.1.0.dist-info/RECORD
