Metadata-Version: 2.1
Name: dataengineeringfunctions
Version: 0.1.0
Summary: This package contains functions commonly used in data engineering tasks.
License: MIT
Author: Rokas Klydzia
Requires-Python: >=3.11,<4.0
Classifier: License :: OSI Approved :: MIT License
Classifier: Programming Language :: Python :: 3
Classifier: Programming Language :: Python :: 3.11
Classifier: Programming Language :: Python :: 3.12
Requires-Dist: numpy (==1.25.2)
